{
  "schemaVersion": "1.0.0",
  "toolId": "json-to-xml",
  "slug": "json-to-xml",
  "name": {
    "en": "JSON to XML Converter",
    "es": "JSON to XML Converter",
    "fr": "JSON to XML Converter",
    "de": "JSON to XML Converter",
    "pt": "JSON to XML Converter"
  },
  "tagline": {
    "en": "Convert JSON data to well-formed XML",
    "es": "Convert JSON data to well-formed XML",
    "fr": "Convert JSON data to well-formed XML",
    "de": "Convert JSON data to well-formed XML",
    "pt": "Convert JSON data to well-formed XML"
  },
  "category": "developer",
  "engine": "developer_engine",
  "engineFn": "devJsonToXml",
  "inputFormats": [
    "text/plain"
  ],
  "outputFormats": [
    {
      "ext": "xml",
      "mime": "application/xml",
      "label": "XML",
      "default": true
    }
  ],
  "batch": {
    "supported": false,
    "maxFiles": 1,
    "zipOutput": false
  },
  "runtime": "browser",
  "uiGroup": "developer",
  "devOptions": {
    "inputPlaceholder": "{\"user\":{\"name\":\"Alice\",\"age\":30}}",
    "sampleInput": "{\"catalog\":{\"book\":[{\"id\":\"bk101\",\"author\":\"Gambardella, Matthew\",\"title\":\"XML Developer's Guide\",\"genre\":\"Computer\",\"price\":44.95},{\"id\":\"bk102\",\"author\":\"Ralls, Kim\",\"title\":\"Midnight Rain\",\"genre\":\"Fantasy\",\"price\":5.95}]}}",
    "outputLabel": "XML Output",
    "runButtonLabel": "Convert to XML",
    "outputType": "text",
    "inputType": "text",
    "livePreview": false,
    "downloadExt": "xml",
    "downloadMime": "application/xml"
  },
  "capabilities": [
    "clipboard-paste"
  ],
  "runtimeHints": {},
  "seo": {
    "primaryKeyword": "json to xml",
    "secondaryKeywords": [
      "convert json to xml",
      "json xml converter",
      "json2xml",
      "transform json to xml"
    ],
    "title": {
      "en": "JSON to XML Converter — DropAnyConvert",
      "es": "JSON to XML Converter — DropAnyConvert",
      "fr": "JSON to XML Converter — DropAnyConvert",
      "de": "JSON to XML Converter — DropAnyConvert",
      "pt": "JSON to XML Converter — DropAnyConvert"
    },
    "description": {
      "en": "Free online json to xml converter. Convert JSON data to well-formed XML No sign-up, no upload, 100% in your browser.",
      "es": "JSON to XML Converter gratuito en línea. Convert JSON data to well-formed XML Sin registro, 100% en tu navegador.",
      "fr": "JSON to XML Converter gratuit en ligne. Convert JSON data to well-formed XML Sans inscription, 100% dans votre navigateur.",
      "de": "Kostenloser JSON to XML Converter online. Convert JSON data to well-formed XML Keine Anmeldung, 100% im Browser.",
      "pt": "JSON to XML Converter online gratuito. Convert JSON data to well-formed XML Sem cadastro, 100% no navegador."
    },
    "h1": {
      "en": "JSON to XML Converter",
      "es": "JSON to XML Converter",
      "fr": "JSON to XML Converter",
      "de": "JSON to XML Converter",
      "pt": "JSON to XML Converter"
    },
    "intro": {
      "en": "JSON to XML Converter: Convert JSON data to well-formed XML. Instant results — everything runs in your browser, nothing is sent to a server.",
      "es": "JSON to XML Converter: Convert JSON data to well-formed XML. Resultados instantáneos — todo funciona en tu navegador, nada se envía a un servidor.",
      "fr": "JSON to XML Converter: Convert JSON data to well-formed XML. Résultats instantanés — tout s'exécute dans votre navigateur, rien n'est envoyé à un serveur.",
      "de": "JSON to XML Converter: Convert JSON data to well-formed XML. Sofortige Ergebnisse — alles läuft in Ihrem Browser, nichts wird an einen Server gesendet.",
      "pt": "JSON to XML Converter: Convert JSON data to well-formed XML. Resultados instantâneos — tudo roda no seu navegador, nada é enviado a um servidor."
    }
  },
  "faq": [
    {
      "question": {
        "en": "How does JSON to XML conversion work?"
      },
      "answer": {
        "en": "JSON objects become XML elements. JSON arrays become repeated elements. JSON keys become element tag names. JSON values become text content or attributes."
      }
    },
    {
      "question": {
        "en": "Can all JSON be converted to XML?"
      },
      "answer": {
        "en": "Most JSON can be converted to valid XML, but JSON keys that start with numbers or contain special characters may need to be sanitized to form valid XML element names."
      }
    },
    {
      "question": {
        "en": "Does the conversion preserve data types?"
      },
      "answer": {
        "en": "XML does not have native number or boolean types — all values are stored as text. The structure is preserved but type information may be lost."
      }
    },
    {
      "question": {
        "en": "Can I convert XML back to JSON?"
      },
      "answer": {
        "en": "Yes. Use the XML to JSON Converter tool to reverse the process."
      }
    }
  ],
  "features": [
    {
      "icon": "lock",
      "title": {
        "en": "100% Private"
      },
      "description": {
        "en": "All processing runs locally in your browser. Nothing is uploaded to any server."
      }
    },
    {
      "icon": "fast",
      "title": {
        "en": "Instant Results"
      },
      "description": {
        "en": "Get results immediately — no waiting for server processing."
      }
    },
    {
      "icon": "device",
      "title": {
        "en": "Works Everywhere"
      },
      "description": {
        "en": "Works on desktop, tablet, and mobile browsers with no installation required."
      }
    },
    {
      "icon": "free",
      "title": {
        "en": "Completely Free"
      },
      "description": {
        "en": "No subscription, no limits, no hidden costs. Free forever."
      }
    }
  ],
  "relatedTools": [
    "xml-to-json",
    "json-formatter",
    "xml-formatter",
    "xml-validator"
  ]
}
